Metadata-Version: 2.1
Name: PyIntegral
Version: 0.0.10
Summary: Integrate arrays, functions numerically using different methods in Python. Original Fortran 2003+ legacy routines date back to 2003-2004. Read the LICENSE.txt file.
Home-page: https://github.com/neutrinomuon/PyIntegral
Author: Jean Gomes
Author-email: antineutrinomuon@gmail.com
License: UNKNOWN
Platform: UNKNOWN
Classifier: Programming Language :: Python :: 3
Classifier: Programming Language :: Fortran
Classifier: Operating System :: OS Independent
License-File: LICENSE.txt
